{
  "ClaimID": "0ab28ee2-d3ab-4cb7-9f25-4e50b0f25650",
  "PolicyID": "c25b9a03-3f98-4035-9576-a9b3e37d2b1b",
  "EffectiveDates": {
    "StartDate": "2023-12-18",
    "EndDate": "2024-12-17"
  },
  "PolicyHolder": {
    "PolicyHolderID": "2edd2830-2862-407f-b54b-d7958dbd8a88",
    "Name": "Emily May",
    "PolicyNumber": "c25b9a03-3f98-4035-9576-a9b3e37d2b1b",
    "ContactInformation": {
      "Phone": "949.291.7578x2020",
      "Email": "karina22@example.com",
      "Address": "194 Kemp Inlet\nSouth Dawn, MA 73357"
    }
  },
  "AccidentDetails": {
    "Date": "2024-10-29",
    "Location": "59548 Lindsey Village\nArthurbury, IA 30294",
    "Description": "Such create sport industry. Purpose prevent defense. Growth woman sing such yard political laugh."
  },
  "Coverage": {
    "BIL": {
      "CoverageLimit": 200000,
      "ClaimedAmount": 44786
    },
    "PDL": {
      "CoverageLimit": 50000,
      "ClaimedAmount": 184774
    },
    "PIP": {
      "CoverageLimit": 50000,
      "ClaimedAmount": 12745
    },
    "CollisionCoverage": {
      "CoverageLimit": 100000,
      "ClaimedAmount": 65919
    },
    "ComprehensiveCoverage": {
      "CoverageLimit": 100000,
      "ClaimedAmount": 1831
    }
  },
  "ClaimStatus": "Approved",
  "ClaimAmounts": {
    "TotalClaimed": 19131,
    "TotalApproved": 9604
  },
  "AdjusterDetails": {
    "Name": "Robert Peterson",
    "ContactInformation": {
      "Phone": "880-359-9898",
      "Email": "rmartin@example.com"
    }
  },
  "SupportingDocuments": [
    {
      "DocumentType": "Repair Estimate",
      "DocumentURL": "http://example.com/documents/55739694-3cbd-443e-9148-7329151d2782"
    }
  ],
  "ClaimHistory": [
    {
      "Status": "Filed",
      "Date": "2024-10-29T14:40:18Z",
      "Notes": "Initial claim filed"
    },
    {
      "Status": "In Review",
      "Date": "2024-11-03T14:40:18Z",
      "Notes": "Claim is being reviewed"
    },
    {
      "Status": "Approved",
      "Date": "2024-11-08T14:40:18Z",
      "Notes": "Claim approved"
    }
  ]
}