{
  "ClaimID": "839d17f7-318b-4dca-9bd8-fd87d34a0c77",
  "PolicyID": "1a5ba983-d7b9-4544-bae9-e1206b60e789",
  "EffectiveDates": {
    "StartDate": "2024-08-19",
    "EndDate": "2025-08-19"
  },
  "PolicyHolder": {
    "PolicyHolderID": "6a655e16-a001-489a-9ce6-25d4de86bdae",
    "Name": "Melinda Yang",
    "PolicyNumber": "1a5ba983-d7b9-4544-bae9-e1206b60e789",
    "ContactInformation": {
      "Phone": "001-262-631-8739x535",
      "Email": "derrickvasquez@example.net",
      "Address": "251 Terry Station\nLake Carrie, IL 45082"
    }
  },
  "AccidentDetails": {
    "Date": "2024-10-13",
    "Location": "12573 Dunn Prairie\nEast Brandi, CT 57877",
    "Description": "Run born sense glass. Wish sometimes your enjoy per. Wear indeed with.\nSociety size money itself body forward election.\nBuild movement final whatever. Entire director again conference body."
  },
  "Coverage": {
    "BIL": {
      "CoverageLimit": 10000,
      "ClaimedAmount": 6607
    },
    "PDL": {
      "CoverageLimit": 100000,
      "ClaimedAmount": 3916
    },
    "PIP": {
      "CoverageLimit": 10000,
      "ClaimedAmount": 99146
    },
    "CollisionCoverage": {
      "CoverageLimit": 200000,
      "ClaimedAmount": 130031
    },
    "ComprehensiveCoverage": {
      "CoverageLimit": 20000,
      "ClaimedAmount": 8908
    }
  },
  "ClaimStatus": "Closed",
  "ClaimAmounts": {
    "TotalClaimed": 143323,
    "TotalApproved": 62942
  },
  "AdjusterDetails": {
    "Name": "Craig Cooper",
    "ContactInformation": {
      "Phone": "(223)595-6587x46364",
      "Email": "elane@example.com"
    }
  },
  "SupportingDocuments": [
    {
      "DocumentType": "Medical Report",
      "DocumentURL": "http://example.com/documents/61d8b5d4-671e-4f59-bccd-113f206713fb"
    }
  ],
  "ClaimHistory": [
    {
      "Status": "Filed",
      "Date": "2024-10-13T14:40:17Z",
      "Notes": "Initial claim filed"
    },
    {
      "Status": "In Review",
      "Date": "2024-10-18T14:40:17Z",
      "Notes": "Claim is being reviewed"
    },
    {
      "Status": "Approved",
      "Date": "2024-10-23T14:40:17Z",
      "Notes": "Claim approved"
    }
  ]
}