{
  "ClaimID": "93254120-a90c-4505-846b-a5935a179666",
  "PolicyID": "6d870df1-64a4-443d-a146-48a6f4d3fa81",
  "EffectiveDates": {
    "StartDate": "2024-06-20",
    "EndDate": "2025-06-20"
  },
  "PolicyHolder": {
    "PolicyHolderID": "30d5b1a9-4da3-4d8e-aa15-e211556b99e6",
    "Name": "Rebecca Fisher",
    "PolicyNumber": "6d870df1-64a4-443d-a146-48a6f4d3fa81",
    "ContactInformation": {
      "Phone": "(230)642-3400",
      "Email": "marshallmatthew@example.net",
      "Address": "765 Moore Meadow Suite 107\nPort Corybury, DC 52462"
    }
  },
  "AccidentDetails": {
    "Date": "2024-08-08",
    "Location": "72250 Stephanie Glens Suite 778\nAnthonyville, NH 90310",
    "Description": "Purpose now less. Body still carry either exactly before once lay. Present yet himself government.\nServe student page gas until team executive. Lawyer people garden to daughter."
  },
  "Coverage": {
    "BIL": {
      "CoverageLimit": 10000,
      "ClaimedAmount": 42274
    },
    "PDL": {
      "CoverageLimit": 100000,
      "ClaimedAmount": 8175
    },
    "PIP": {
      "CoverageLimit": 10000,
      "ClaimedAmount": 9875
    },
    "CollisionCoverage": {
      "CoverageLimit": 20000,
      "ClaimedAmount": 46388
    },
    "ComprehensiveCoverage": {
      "CoverageLimit": 100000,
      "ClaimedAmount": 30108
    }
  },
  "ClaimStatus": "Filed",
  "ClaimAmounts": {
    "TotalClaimed": 37794,
    "TotalApproved": 6753
  },
  "AdjusterDetails": {
    "Name": "John Ward",
    "ContactInformation": {
      "Phone": "(694)488-0560x933",
      "Email": "suttonbrenda@example.org"
    }
  },
  "SupportingDocuments": [
    {
      "DocumentType": "Witness Statement",
      "DocumentURL": "http://example.com/documents/6c9ab08a-cdba-42c0-ab53-e86acbc29885"
    }
  ],
  "ClaimHistory": [
    {
      "Status": "Filed",
      "Date": "2024-08-08T14:40:18Z",
      "Notes": "Initial claim filed"
    },
    {
      "Status": "In Review",
      "Date": "2024-08-13T14:40:18Z",
      "Notes": "Claim is being reviewed"
    },
    {
      "Status": "Approved",
      "Date": "2024-08-18T14:40:18Z",
      "Notes": "Claim approved"
    }
  ]
}