{
  "ClaimID": "ce44b43e-7683-4d2c-99e5-36b3506ecfb3",
  "PolicyID": "34493b85-e870-4a43-ac0b-f1efc91805d7",
  "EffectiveDates": {
    "StartDate": "2024-04-24",
    "EndDate": "2025-04-24"
  },
  "PolicyHolder": {
    "PolicyHolderID": "8ee757f2-2114-47fa-b23a-8e7525bf8215",
    "Name": "Paul James",
    "PolicyNumber": "34493b85-e870-4a43-ac0b-f1efc91805d7",
    "ContactInformation": {
      "Phone": "402-582-1648x54770",
      "Email": "lisa97@example.com",
      "Address": "94970 Henry Via\nCooperport, MS 65834"
    }
  },
  "AccidentDetails": {
    "Date": "2024-08-26",
    "Location": "151 Stephen Mountains\nEast Tiffanyside, DC 82448",
    "Description": "True attention measure room hour probably this start. Forward near throw soon.\nSit wish build friend score right rather. Adult movement top the."
  },
  "Coverage": {
    "BIL": {
      "CoverageLimit": 200000,
      "ClaimedAmount": 30291
    },
    "PDL": {
      "CoverageLimit": 10000,
      "ClaimedAmount": 34520
    },
    "PIP": {
      "CoverageLimit": 200000,
      "ClaimedAmount": 87892
    },
    "CollisionCoverage": {
      "CoverageLimit": 100000,
      "ClaimedAmount": 22169
    },
    "ComprehensiveCoverage": {
      "CoverageLimit": 20000,
      "ClaimedAmount": 3876
    }
  },
  "ClaimStatus": "Filed",
  "ClaimAmounts": {
    "TotalClaimed": 147209,
    "TotalApproved": 41937
  },
  "AdjusterDetails": {
    "Name": "Morgan Chandler",
    "ContactInformation": {
      "Phone": "(776)857-2438",
      "Email": "fclark@example.org"
    }
  },
  "SupportingDocuments": [
    {
      "DocumentType": "Repair Estimate",
      "DocumentURL": "http://example.com/documents/fa993c89-56f3-4f30-a45c-e02a9b333451"
    }
  ],
  "ClaimHistory": [
    {
      "Status": "Filed",
      "Date": "2024-08-26T14:40:18Z",
      "Notes": "Initial claim filed"
    },
    {
      "Status": "In Review",
      "Date": "2024-08-31T14:40:18Z",
      "Notes": "Claim is being reviewed"
    },
    {
      "Status": "Approved",
      "Date": "2024-09-05T14:40:18Z",
      "Notes": "Claim approved"
    }
  ]
}