{
  "ClaimID": "d4b73c05-3728-41a0-bf98-300eb970e7cd",
  "PolicyID": "059efcc9-b84d-4775-b053-553f7097a6cd",
  "EffectiveDates": {
    "StartDate": "2024-03-27",
    "EndDate": "2025-03-27"
  },
  "PolicyHolder": {
    "PolicyHolderID": "135143c0-a4cf-46da-bd20-74e51c8bcc93",
    "Name": "Christopher Reyes",
    "PolicyNumber": "059efcc9-b84d-4775-b053-553f7097a6cd",
    "ContactInformation": {
      "Phone": "001-657-314-5172x1688",
      "Email": "krameremily@example.com",
      "Address": "Unit 7768 Box 5696\nDPO AP 42143"
    }
  },
  "AccidentDetails": {
    "Date": "2024-09-11",
    "Location": "492 Kiara Terrace Apt. 011\nWalkerbury, SC 49356",
    "Description": "Analysis want remember event though put ever. Because friend summer street.\nParent wear week. See continue assume. Design artist force."
  },
  "Coverage": {
    "BIL": {
      "CoverageLimit": 200000,
      "ClaimedAmount": 45038
    },
    "PDL": {
      "CoverageLimit": 20000,
      "ClaimedAmount": 5436
    },
    "PIP": {
      "CoverageLimit": 10000,
      "ClaimedAmount": 2084
    },
    "CollisionCoverage": {
      "CoverageLimit": 100000,
      "ClaimedAmount": 13686
    },
    "ComprehensiveCoverage": {
      "CoverageLimit": 10000,
      "ClaimedAmount": 5744
    }
  },
  "ClaimStatus": "Approved",
  "ClaimAmounts": {
    "TotalClaimed": 166425,
    "TotalApproved": 118505
  },
  "AdjusterDetails": {
    "Name": "Theodore Velez",
    "ContactInformation": {
      "Phone": "2962617232",
      "Email": "joyce39@example.org"
    }
  },
  "SupportingDocuments": [
    {
      "DocumentType": "Witness Statement",
      "DocumentURL": "http://example.com/documents/3f59dca5-1947-46cd-b6cb-44c3200fe449"
    }
  ],
  "ClaimHistory": [
    {
      "Status": "Filed",
      "Date": "2024-09-11T14:40:19Z",
      "Notes": "Initial claim filed"
    },
    {
      "Status": "In Review",
      "Date": "2024-09-16T14:40:19Z",
      "Notes": "Claim is being reviewed"
    },
    {
      "Status": "Approved",
      "Date": "2024-09-21T14:40:19Z",
      "Notes": "Claim approved"
    }
  ]
}