{
    "ClaimID": "05e40f51-01c9-4534-8202-d962df8bc3b0",
    "PolicyID": "dfc5f207-f97e-423e-8fca-25cb90f59c79",
    "EffectiveDates": {
        "StartDate": "2024-02-07",
        "EndDate": "2025-02-06"
    },
    "PolicyHolder": {
        "PolicyHolderID": "21ed7ece-c2c9-4584-a99d-43b035d20124",
        "Name": "Phyllis Sims",
        "PolicyNumber": "dfc5f207-f97e-423e-8fca-25cb90f59c79",
        "ContactInformation": {
            "Phone": "+1-928-994-9541x3608",
            "Email": "marc26@example.com",
            "Address": "2812 Dawn Centers\nHernandezland, SD 37867"
        }
    },
    "AccidentDetails": {
        "Date": "2024-06-01",
        "Location": "397 Autumn Expressway Apt. 449\nNew Steven, SD 27956",
        "Description": "Analysis few relate team site likely. Social doctor keep song seven. Experience education more law customer level.\nCampaign cause create true knowledge long station."
    },
    "Coverage": {
        "BIL": {
            "CoverageLimit": 100000,
            "ClaimedAmount": 6779
        },
        "PDL": {
            "CoverageLimit": 10000,
            "ClaimedAmount": 2438
        },
        "PIP": {
            "CoverageLimit": 100000,
            "ClaimedAmount": 17049
        },
        "CollisionCoverage": {
            "CoverageLimit": 10000,
            "ClaimedAmount": 27431
        },
        "ComprehensiveCoverage": {
            "CoverageLimit": 100000,
            "ClaimedAmount": 5368
        }
    },
    "ClaimStatus": "Closed",
    "ClaimAmounts": {
        "TotalClaimed": 113021,
        "TotalApproved": 67839
    },
    "AdjusterDetails": {
        "Name": "Scott Cruz",
        "ContactInformation": {
            "Phone": "+1-745-569-3012x30764",
            "Email": "juliebooth@example.net"
        }
    },
    "SupportingDocuments": [
        {
            "DocumentType": "Medical Report",
            "DocumentURL": "http://example.com/documents/aec26ac2-6d35-4e7f-8bfd-067dec3e84b5"
        }
    ],
    "ClaimHistory": [
        {
            "Status": "Filed",
            "Date": "2024-06-01T14:39:15Z",
            "Notes": "Initial claim filed"
        },
        {
            "Status": "In Review",
            "Date": "2024-06-06T14:39:15Z",
            "Notes": "Claim is being reviewed"
        },
        {
            "Status": "Approved",
            "Date": "2024-06-11T14:39:15Z",
            "Notes": "Claim approved"
        }
    ],
    "FraudLikelihood": "low"
}