{
    "ClaimID": "2741381f-743e-43eb-a443-d005778d4e10",
    "PolicyID": "b4d4252b-5804-4cf3-841c-b884806b570a",
    "EffectiveDates": {
        "StartDate": "2024-01-15",
        "EndDate": "2025-01-14"
    },
    "PolicyHolder": {
        "PolicyHolderID": "fdfd5593-3642-425d-b5b1-d51a37bffe29",
        "Name": "Joyce Vang",
        "PolicyNumber": "b4d4252b-5804-4cf3-841c-b884806b570a",
        "ContactInformation": {
            "Phone": "816.551.6922x820",
            "Email": "ksmith@example.org",
            "Address": "36069 Antonio Forges\nSouth Ann, GU 82963"
        }
    },
    "AccidentDetails": {
        "Date": "2024-02-17",
        "Location": "28404 Melendez Meadows Suite 980\nPort Gregory, AR 47328",
        "Description": "Program couple price memory television watch expect response. Book mean range stop or.\nBuilding clearly role lay organization. Power town thus. Money suffer yard increase sometimes."
    },
    "Coverage": {
        "BIL": {
            "CoverageLimit": 50000,
            "ClaimedAmount": 5152
        },
        "PDL": {
            "CoverageLimit": 200000,
            "ClaimedAmount": 2379
        },
        "PIP": {
            "CoverageLimit": 20000,
            "ClaimedAmount": 185112
        },
        "CollisionCoverage": {
            "CoverageLimit": 20000,
            "ClaimedAmount": 8631
        },
        "ComprehensiveCoverage": {
            "CoverageLimit": 200000,
            "ClaimedAmount": 32794
        }
    },
    "ClaimStatus": "Closed",
    "ClaimAmounts": {
        "TotalClaimed": 42353,
        "TotalApproved": 32473
    },
    "AdjusterDetails": {
        "Name": "Heather Stone",
        "ContactInformation": {
            "Phone": "(877)429-4481",
            "Email": "williamramirez@example.net"
        }
    },
    "SupportingDocuments": [
        {
            "DocumentType": "Medical Report",
            "DocumentURL": "http://example.com/documents/ca2634eb-d7e7-4b1a-bc17-7c0437d2d239"
        }
    ],
    "ClaimHistory": [
        {
            "Status": "Filed",
            "Date": "2024-02-17T14:40:18Z",
            "Notes": "Initial claim filed"
        },
        {
            "Status": "In Review",
            "Date": "2024-02-22T14:40:18Z",
            "Notes": "Claim is being reviewed"
        },
        {
            "Status": "Approved",
            "Date": "2024-02-27T14:40:18Z",
            "Notes": "Claim approved"
        }
    ],
    "FraudLikelihood": "low"
}