{
    "ClaimID": "377864cf-5fb3-461e-aa2e-927d1dc26d68",
    "PolicyID": "148b8eed-1046-422f-9dd6-29faee8d471f",
    "EffectiveDates": {
        "StartDate": "2024-03-23",
        "EndDate": "2025-03-23"
    },
    "PolicyHolder": {
        "PolicyHolderID": "a7ef9cdb-8102-409a-b9da-de873f7ede12",
        "Name": "Michael Lawson",
        "PolicyNumber": "148b8eed-1046-422f-9dd6-29faee8d471f",
        "ContactInformation": {
            "Phone": "283.333.7857",
            "Email": "ndavidson@example.com",
            "Address": "7337 Crosby Forge\nTanyamouth, LA 77868"
        }
    },
    "AccidentDetails": {
        "Date": "2024-04-28",
        "Location": "40370 Joseph Isle Suite 889\nHayestown, VI 16435",
        "Description": "Social model especially mouth. Television society face but agent call audience benefit. He media material."
    },
    "Coverage": {
        "BIL": {
            "CoverageLimit": 200000,
            "ClaimedAmount": 51176
        },
        "PDL": {
            "CoverageLimit": 100000,
            "ClaimedAmount": 104074
        },
        "PIP": {
            "CoverageLimit": 10000,
            "ClaimedAmount": 1469
        },
        "CollisionCoverage": {
            "CoverageLimit": 50000,
            "ClaimedAmount": 22674
        },
        "ComprehensiveCoverage": {
            "CoverageLimit": 20000,
            "ClaimedAmount": 19466
        }
    },
    "ClaimStatus": "Filed",
    "ClaimAmounts": {
        "TotalClaimed": 116199,
        "TotalApproved": 50950
    },
    "AdjusterDetails": {
        "Name": "Ana White",
        "ContactInformation": {
            "Phone": "7427411868",
            "Email": "xjones@example.com"
        }
    },
    "SupportingDocuments": [
        {
            "DocumentType": "Witness Statement",
            "DocumentURL": "http://example.com/documents/dcfa2e19-1429-4a9b-ba35-2ef2b088311d"
        }
    ],
    "ClaimHistory": [
        {
            "Status": "Filed",
            "Date": "2024-04-28T14:40:16Z",
            "Notes": "Initial claim filed"
        },
        {
            "Status": "In Review",
            "Date": "2024-05-03T14:40:16Z",
            "Notes": "Claim is being reviewed"
        },
        {
            "Status": "Approved",
            "Date": "2024-05-08T14:40:16Z",
            "Notes": "Claim approved"
        }
    ],
    "FraudLikelihood": "low"
}