{
    "ClaimID": "3806884a-b134-4214-a23b-d26e42eee965",
    "PolicyID": "b6420836-b74a-40a7-938b-dfa817059121",
    "EffectiveDates": {
        "StartDate": "2024-07-15",
        "EndDate": "2025-07-15"
    },
    "PolicyHolder": {
        "PolicyHolderID": "f55d46f4-1e49-4932-8a4a-f8e41da951a9",
        "Name": "Emily Guzman",
        "PolicyNumber": "b6420836-b74a-40a7-938b-dfa817059121",
        "ContactInformation": {
            "Phone": "(788)925-7038x676",
            "Email": "taylor65@example.org",
            "Address": "04769 Gina Prairie Suite 444\nNunezberg, NM 70829"
        }
    },
    "AccidentDetails": {
        "Date": "2025-02-04",
        "Location": "8194 Angela Neck\nJaredfurt, HI 90274",
        "Description": "Easy too put tree until different. Beautiful government performance I.\nSouthern under test need. Onto unit husband price culture rock."
    },
    "Coverage": {
        "BIL": {
            "CoverageLimit": 50000,
            "ClaimedAmount": 118091
        },
        "PDL": {
            "CoverageLimit": 50000,
            "ClaimedAmount": 4116
        },
        "PIP": {
            "CoverageLimit": 20000,
            "ClaimedAmount": 137402
        },
        "CollisionCoverage": {
            "CoverageLimit": 50000,
            "ClaimedAmount": 192538
        },
        "ComprehensiveCoverage": {
            "CoverageLimit": 50000,
            "ClaimedAmount": 42664
        }
    },
    "ClaimStatus": "In Review",
    "ClaimAmounts": {
        "TotalClaimed": 20647,
        "TotalApproved": 16376
    },
    "AdjusterDetails": {
        "Name": "Sonia Mccullough",
        "ContactInformation": {
            "Phone": "(996)404-5447x2177",
            "Email": "samanthawalsh@example.com"
        }
    },
    "SupportingDocuments": [
        {
            "DocumentType": "Police Report",
            "DocumentURL": "http://example.com/documents/07ba404f-2b85-4fd9-a656-ad3b4f2a2b2f"
        }
    ],
    "ClaimHistory": [
        {
            "Status": "Filed",
            "Date": "2025-02-04T14:40:18Z",
            "Notes": "Initial claim filed"
        },
        {
            "Status": "In Review",
            "Date": "2025-02-09T14:40:18Z",
            "Notes": "Claim is being reviewed"
        },
        {
            "Status": "Approved",
            "Date": "2025-02-14T14:40:18Z",
            "Notes": "Claim approved"
        }
    ],
    "FraudLikelihood": "low"
}