{
    "ClaimID": "4642921d-0e0f-4e47-855f-07e4fd61ba6c",
    "PolicyID": "ca132daa-e4fd-4ce2-8a64-6575103f46ea",
    "EffectiveDates": {
        "StartDate": "2023-11-21",
        "EndDate": "2024-11-20"
    },
    "PolicyHolder": {
        "PolicyHolderID": "0b7eff3f-c5a9-40a7-a362-c8c100315aad",
        "Name": "Robert Clark",
        "PolicyNumber": "ca132daa-e4fd-4ce2-8a64-6575103f46ea",
        "ContactInformation": {
            "Phone": "001-533-582-5831x39042",
            "Email": "jhernandez@example.com",
            "Address": "47657 Trujillo Green Suite 315\nPort Carolynmouth, NH 30849"
        }
    },
    "AccidentDetails": {
        "Date": "2024-10-21",
        "Location": "85201 Christopher Drive Apt. 463\nWest Jill, TN 11104",
        "Description": "Travel cell but away son soldier investment. Matter man foot role laugh would contain.\nDoor business south. Too dark would local meet discuss PM price. Onto yet large cultural."
    },
    "Coverage": {
        "BIL": {
            "CoverageLimit": 50000,
            "ClaimedAmount": 9517
        },
        "PDL": {
            "CoverageLimit": 10000,
            "ClaimedAmount": 4188
        },
        "PIP": {
            "CoverageLimit": 20000,
            "ClaimedAmount": 42069
        },
        "CollisionCoverage": {
            "CoverageLimit": 50000,
            "ClaimedAmount": 5475
        },
        "ComprehensiveCoverage": {
            "CoverageLimit": 100000,
            "ClaimedAmount": 37869
        }
    },
    "ClaimStatus": "Closed",
    "ClaimAmounts": {
        "TotalClaimed": 182269,
        "TotalApproved": 24211
    },
    "AdjusterDetails": {
        "Name": "Ruben Sanchez",
        "ContactInformation": {
            "Phone": "001-279-450-7186x5441",
            "Email": "lauren07@example.org"
        }
    },
    "SupportingDocuments": [
        {
            "DocumentType": "Medical Report",
            "DocumentURL": "http://example.com/documents/f9a961cc-3850-4223-bf3c-5839abbf54ac"
        }
    ],
    "ClaimHistory": [
        {
            "Status": "Filed",
            "Date": "2024-10-21T14:27:53Z",
            "Notes": "Initial claim filed"
        },
        {
            "Status": "In Review",
            "Date": "2024-10-26T14:27:53Z",
            "Notes": "Claim is being reviewed"
        },
        {
            "Status": "Approved",
            "Date": "2024-10-31T14:27:53Z",
            "Notes": "Claim approved"
        }
    ],
    "FraudLikelihood": "low"
}