{
    "ClaimID": "5c2ef153-e3b0-49e1-b20e-b43d01fa6d2d",
    "PolicyID": "409b0ecb-02f6-4dc7-987b-e17b9a8364f0",
    "EffectiveDates": {
        "StartDate": "2024-04-28",
        "EndDate": "2025-04-28"
    },
    "PolicyHolder": {
        "PolicyHolderID": "e5548ad4-c1e8-4d86-9ea1-7ae665f80540",
        "Name": "Laurie Bush",
        "PolicyNumber": "409b0ecb-02f6-4dc7-987b-e17b9a8364f0",
        "ContactInformation": {
            "Phone": "(242)735-6229",
            "Email": "mguzman@example.com",
            "Address": "2013 Brandon Glen\nAndersonhaven, NV 99570"
        }
    },
    "AccidentDetails": {
        "Date": "2025-03-15",
        "Location": "249 Diaz Village\nHoffmanhaven, FL 16918",
        "Description": "Health experience expert worker necessary but let. Friend among eye energy close. Where generation sense third.\nHow better cost positive buy policy indicate than. Know among never."
    },
    "Coverage": {
        "BIL": {
            "CoverageLimit": 10000,
            "ClaimedAmount": 45223
        },
        "PDL": {
            "CoverageLimit": 200000,
            "ClaimedAmount": 44100
        },
        "PIP": {
            "CoverageLimit": 10000,
            "ClaimedAmount": 21513
        },
        "CollisionCoverage": {
            "CoverageLimit": 100000,
            "ClaimedAmount": 21429
        },
        "ComprehensiveCoverage": {
            "CoverageLimit": 10000,
            "ClaimedAmount": 3870
        }
    },
    "ClaimStatus": "Approved",
    "ClaimAmounts": {
        "TotalClaimed": 36822,
        "TotalApproved": 34120
    },
    "AdjusterDetails": {
        "Name": "Harry Vargas",
        "ContactInformation": {
            "Phone": "671.579.5196x0618",
            "Email": "tvillarreal@example.net"
        }
    },
    "SupportingDocuments": [
        {
            "DocumentType": "Police Report",
            "DocumentURL": "http://example.com/documents/5f2370d9-d734-4e47-8e85-c086efc96ca0"
        }
    ],
    "ClaimHistory": [
        {
            "Status": "Filed",
            "Date": "2025-03-15T14:39:15Z",
            "Notes": "Initial claim filed"
        },
        {
            "Status": "In Review",
            "Date": "2025-03-20T14:39:15Z",
            "Notes": "Claim is being reviewed"
        },
        {
            "Status": "Approved",
            "Date": "2025-03-25T14:39:15Z",
            "Notes": "Claim approved"
        }
    ],
    "FraudLikelihood": "low"
}