{
    "ClaimID": "6b190963-3509-46e2-97e0-8cba6eceb003",
    "PolicyID": "0dc3ae63-27cb-4180-8126-adf86d18ff44",
    "EffectiveDates": {
        "StartDate": "2024-08-25",
        "EndDate": "2025-08-25"
    },
    "PolicyHolder": {
        "PolicyHolderID": "d01a9033-d221-47fa-b203-799bdac2c6bc",
        "Name": "Nicholas Berg",
        "PolicyNumber": "0dc3ae63-27cb-4180-8126-adf86d18ff44",
        "ContactInformation": {
            "Phone": "(601)972-3147",
            "Email": "anna18@example.net",
            "Address": "16017 Compton Ports Suite 827\nSouth Lee, GU 06812"
        }
    },
    "AccidentDetails": {
        "Date": "2024-09-03",
        "Location": "262 Bruce Meadow\nSouth Mark, NH 67264",
        "Description": "When newspaper performance scene partner. Light about newspaper it political serve. Compare strategy across game way ask.\nModern project him human. Plan affect not professor fall."
    },
    "Coverage": {
        "BIL": {
            "CoverageLimit": 50000,
            "ClaimedAmount": 34582
        },
        "PDL": {
            "CoverageLimit": 200000,
            "ClaimedAmount": 11586
        },
        "PIP": {
            "CoverageLimit": 50000,
            "ClaimedAmount": 2738
        },
        "CollisionCoverage": {
            "CoverageLimit": 200000,
            "ClaimedAmount": 49016
        },
        "ComprehensiveCoverage": {
            "CoverageLimit": 10000,
            "ClaimedAmount": 15328
        }
    },
    "ClaimStatus": "Approved",
    "ClaimAmounts": {
        "TotalClaimed": 30249,
        "TotalApproved": 17682
    },
    "AdjusterDetails": {
        "Name": "Laura Hess",
        "ContactInformation": {
            "Phone": "952.986.5919x987",
            "Email": "sarahhughes@example.com"
        }
    },
    "SupportingDocuments": [
        {
            "DocumentType": "Witness Statement",
            "DocumentURL": "http://example.com/documents/059470d0-4b51-41c2-963a-fbc1e2633172"
        }
    ],
    "ClaimHistory": [
        {
            "Status": "Filed",
            "Date": "2024-09-03T14:27:53Z",
            "Notes": "Initial claim filed"
        },
        {
            "Status": "In Review",
            "Date": "2024-09-08T14:27:53Z",
            "Notes": "Claim is being reviewed"
        },
        {
            "Status": "Approved",
            "Date": "2024-09-13T14:27:53Z",
            "Notes": "Claim approved"
        }
    ],
    "FraudLikelihood": "low"
}