{
    "ClaimID": "7ab5640e-fde8-4f1e-8c82-df4f4aa00c58",
    "PolicyID": "1337e824-617c-4fda-a43f-9d31db57734c",
    "EffectiveDates": {
        "StartDate": "2024-02-02",
        "EndDate": "2025-02-01"
    },
    "PolicyHolder": {
        "PolicyHolderID": "d015e258-01aa-448a-b127-bd46fcf5c28e",
        "Name": "Mark Carter",
        "PolicyNumber": "1337e824-617c-4fda-a43f-9d31db57734c",
        "ContactInformation": {
            "Phone": "001-328-941-1488x619",
            "Email": "ellisdylan@example.net",
            "Address": "886 Cobb Gardens Suite 248\nWest Codyton, NJ 36960"
        }
    },
    "AccidentDetails": {
        "Date": "2024-04-24",
        "Location": "Unit 4624 Box 3759\nDPO AA 23448",
        "Description": "Financial ask forward. Hair major difference forward feel data trade make. Happen these just debate decision."
    },
    "Coverage": {
        "BIL": {
            "CoverageLimit": 100000,
            "ClaimedAmount": 7270
        },
        "PDL": {
            "CoverageLimit": 20000,
            "ClaimedAmount": 3911
        },
        "PIP": {
            "CoverageLimit": 200000,
            "ClaimedAmount": 8279
        },
        "CollisionCoverage": {
            "CoverageLimit": 20000,
            "ClaimedAmount": 1388
        },
        "ComprehensiveCoverage": {
            "CoverageLimit": 20000,
            "ClaimedAmount": 32559
        }
    },
    "ClaimStatus": "In Review",
    "ClaimAmounts": {
        "TotalClaimed": 198163,
        "TotalApproved": 159885
    },
    "AdjusterDetails": {
        "Name": "Brian Duncan",
        "ContactInformation": {
            "Phone": "(214)505-0218x53983",
            "Email": "millerbrian@example.org"
        }
    },
    "SupportingDocuments": [
        {
            "DocumentType": "Medical Report",
            "DocumentURL": "http://example.com/documents/489fa75a-0a74-4b77-88a2-b90ea86b5b9e"
        }
    ],
    "ClaimHistory": [
        {
            "Status": "Filed",
            "Date": "2024-04-24T14:40:18Z",
            "Notes": "Initial claim filed"
        },
        {
            "Status": "In Review",
            "Date": "2024-04-29T14:40:18Z",
            "Notes": "Claim is being reviewed"
        },
        {
            "Status": "Approved",
            "Date": "2024-05-04T14:40:18Z",
            "Notes": "Claim approved"
        }
    ],
    "FraudLikelihood": "low"
}