{
    "ClaimID": "939e1eeb-ba02-4db0-b5de-37f2e1c9f3fd",
    "PolicyID": "19eff174-f091-4cd8-a9f6-dbe46b19c1a3",
    "EffectiveDates": {
        "StartDate": "2024-07-17",
        "EndDate": "2025-07-17"
    },
    "PolicyHolder": {
        "PolicyHolderID": "b1429bb6-4a41-4a27-8dfc-4927efd07673",
        "Name": "Eric Johnson",
        "PolicyNumber": "19eff174-f091-4cd8-a9f6-dbe46b19c1a3",
        "ContactInformation": {
            "Phone": "(764)900-0355x7467",
            "Email": "pscott@example.org",
            "Address": "PSC 1525, Box 9190\nAPO AE 71256"
        }
    },
    "AccidentDetails": {
        "Date": "2024-10-26",
        "Location": "9948 Alyssa Mountains Suite 899\nFowlerville, LA 48878",
        "Description": "Social approach stay hospital entire matter. Movement compare relationship also majority international suffer. Official resource through pass institution. Or make could method month same."
    },
    "Coverage": {
        "BIL": {
            "CoverageLimit": 200000,
            "ClaimedAmount": 71553
        },
        "PDL": {
            "CoverageLimit": 10000,
            "ClaimedAmount": 22429
        },
        "PIP": {
            "CoverageLimit": 200000,
            "ClaimedAmount": 117494
        },
        "CollisionCoverage": {
            "CoverageLimit": 200000,
            "ClaimedAmount": 86045
        },
        "ComprehensiveCoverage": {
            "CoverageLimit": 100000,
            "ClaimedAmount": 23830
        }
    },
    "ClaimStatus": "In Review",
    "ClaimAmounts": {
        "TotalClaimed": 159791,
        "TotalApproved": 127464
    },
    "AdjusterDetails": {
        "Name": "Suzanne Perez",
        "ContactInformation": {
            "Phone": "546.768.7153x5777",
            "Email": "michaelhoward@example.org"
        }
    },
    "SupportingDocuments": [
        {
            "DocumentType": "Witness Statement",
            "DocumentURL": "http://example.com/documents/861869ef-d086-4cba-ab92-0b3453c622ee"
        }
    ],
    "ClaimHistory": [
        {
            "Status": "Filed",
            "Date": "2024-10-26T14:27:53Z",
            "Notes": "Initial claim filed"
        },
        {
            "Status": "In Review",
            "Date": "2024-10-31T14:27:53Z",
            "Notes": "Claim is being reviewed"
        },
        {
            "Status": "Approved",
            "Date": "2024-11-05T14:27:53Z",
            "Notes": "Claim approved"
        }
    ],
    "FraudLikelihood": "low"
}