{
    "ClaimID": "a116a71f-d79b-453a-9498-b62a8011a6eb",
    "PolicyID": "c4ffcf47-6cce-4f52-977d-c68cb14b32b8",
    "EffectiveDates": {
        "StartDate": "2024-05-02",
        "EndDate": "2025-05-02"
    },
    "PolicyHolder": {
        "PolicyHolderID": "4b3c598d-9b47-467b-a797-7ac0fc2c6468",
        "Name": "Shawn Hill",
        "PolicyNumber": "c4ffcf47-6cce-4f52-977d-c68cb14b32b8",
        "ContactInformation": {
            "Phone": "848-228-7516x725",
            "Email": "jenningsanthony@example.com",
            "Address": "524 Pamela Grove Suite 326\nNew Kelsey, VT 79190"
        }
    },
    "AccidentDetails": {
        "Date": "2024-08-05",
        "Location": "72048 Reyes Pass\nLake Jeremy, NV 84425",
        "Description": "Dream body later ten like response. Add house stock Republican remain."
    },
    "Coverage": {
        "BIL": {
            "CoverageLimit": 10000,
            "ClaimedAmount": 13644
        },
        "PDL": {
            "CoverageLimit": 20000,
            "ClaimedAmount": 5198
        },
        "PIP": {
            "CoverageLimit": 10000,
            "ClaimedAmount": 9522
        },
        "CollisionCoverage": {
            "CoverageLimit": 20000,
            "ClaimedAmount": 66152
        },
        "ComprehensiveCoverage": {
            "CoverageLimit": 100000,
            "ClaimedAmount": 79178
        }
    },
    "ClaimStatus": "Filed",
    "ClaimAmounts": {
        "TotalClaimed": 56938,
        "TotalApproved": 56251
    },
    "AdjusterDetails": {
        "Name": "Katie Riley",
        "ContactInformation": {
            "Phone": "+1-226-234-5362x73763",
            "Email": "jimmyrussell@example.net"
        }
    },
    "SupportingDocuments": [
        {
            "DocumentType": "Repair Estimate",
            "DocumentURL": "http://example.com/documents/e9890af6-856f-47c3-8a94-fdeec6e3b8ac"
        }
    ],
    "ClaimHistory": [
        {
            "Status": "Filed",
            "Date": "2024-08-05T14:40:17Z",
            "Notes": "Initial claim filed"
        },
        {
            "Status": "In Review",
            "Date": "2024-08-10T14:40:17Z",
            "Notes": "Claim is being reviewed"
        },
        {
            "Status": "Approved",
            "Date": "2024-08-15T14:40:17Z",
            "Notes": "Claim approved"
        }
    ],
    "FraudLikelihood": "low"
}