{
    "ClaimID": "ab3be1d7-d0cf-40b4-9420-1b7543fc379f",
    "PolicyID": "8de979df-d9c1-426b-ae19-8b63d7ab59df",
    "EffectiveDates": {
        "StartDate": "2023-11-22",
        "EndDate": "2024-11-21"
    },
    "PolicyHolder": {
        "PolicyHolderID": "272189f7-59e4-4443-bd3a-8d331e5e0b54",
        "Name": "Derek Hoover",
        "PolicyNumber": "8de979df-d9c1-426b-ae19-8b63d7ab59df",
        "ContactInformation": {
            "Phone": "(544)588-2939",
            "Email": "nicoleflores@example.org",
            "Address": "PSC 9232, Box 1671\nAPO AE 12822"
        }
    },
    "AccidentDetails": {
        "Date": "2024-03-22",
        "Location": "73078 Cameron Prairie Suite 552\nMariahaven, UT 58474",
        "Description": "Brother which carry back ten. Left industry bank lot until official. Large training may bit keep agree.\nEven these both. Officer analysis support firm character seven prove attack. Sort hard too."
    },
    "Coverage": {
        "BIL": {
            "CoverageLimit": 50000,
            "ClaimedAmount": 7041
        },
        "PDL": {
            "CoverageLimit": 20000,
            "ClaimedAmount": 12497
        },
        "PIP": {
            "CoverageLimit": 10000,
            "ClaimedAmount": 44981
        },
        "CollisionCoverage": {
            "CoverageLimit": 50000,
            "ClaimedAmount": 3505
        },
        "ComprehensiveCoverage": {
            "CoverageLimit": 20000,
            "ClaimedAmount": 157280
        }
    },
    "ClaimStatus": "Approved",
    "ClaimAmounts": {
        "TotalClaimed": 50908,
        "TotalApproved": 29612
    },
    "AdjusterDetails": {
        "Name": "Ashley Martin",
        "ContactInformation": {
            "Phone": "(511)248-3428x549",
            "Email": "ilove@example.net"
        }
    },
    "SupportingDocuments": [
        {
            "DocumentType": "Repair Estimate",
            "DocumentURL": "http://example.com/documents/0efd5fed-6c40-4395-9509-c85b12bc303e"
        }
    ],
    "ClaimHistory": [
        {
            "Status": "Filed",
            "Date": "2024-03-22T14:14:31Z",
            "Notes": "Initial claim filed"
        },
        {
            "Status": "In Review",
            "Date": "2024-03-27T14:14:31Z",
            "Notes": "Claim is being reviewed"
        },
        {
            "Status": "Approved",
            "Date": "2024-04-01T14:14:31Z",
            "Notes": "Claim approved"
        }
    ],
    "FraudLikelihood": "low"
}