{
    "ClaimID": "bbf7123f-6e35-4517-83fd-7fe0098fc27b",
    "PolicyID": "4932ecdd-edc7-4356-ab5e-d7bc3d48c5e6",
    "EffectiveDates": {
        "StartDate": "2024-06-10",
        "EndDate": "2025-06-10"
    },
    "PolicyHolder": {
        "PolicyHolderID": "267d3988-cc8c-4899-a118-5597c0be4184",
        "Name": "Theresa Ellison",
        "PolicyNumber": "4932ecdd-edc7-4356-ab5e-d7bc3d48c5e6",
        "ContactInformation": {
            "Phone": "6308608822",
            "Email": "eric61@example.net",
            "Address": "PSC 0036, Box 9432\nAPO AA 58731"
        }
    },
    "AccidentDetails": {
        "Date": "2025-03-11",
        "Location": "1547 Rodgers Square Apt. 545\nMelissachester, MO 81486",
        "Description": "Power sport program cup wonder race produce. Might story north southern. Wall report our reflect scientist might."
    },
    "Coverage": {
        "BIL": {
            "CoverageLimit": 10000,
            "ClaimedAmount": 9966
        },
        "PDL": {
            "CoverageLimit": 200000,
            "ClaimedAmount": 42973
        },
        "PIP": {
            "CoverageLimit": 20000,
            "ClaimedAmount": 11429
        },
        "CollisionCoverage": {
            "CoverageLimit": 200000,
            "ClaimedAmount": 2945
        },
        "ComprehensiveCoverage": {
            "CoverageLimit": 100000,
            "ClaimedAmount": 13233
        }
    },
    "ClaimStatus": "Filed",
    "ClaimAmounts": {
        "TotalClaimed": 196747,
        "TotalApproved": 72266
    },
    "AdjusterDetails": {
        "Name": "Brittany Rodriguez",
        "ContactInformation": {
            "Phone": "870-642-9379x120",
            "Email": "tracy15@example.net"
        }
    },
    "SupportingDocuments": [
        {
            "DocumentType": "Repair Estimate",
            "DocumentURL": "http://example.com/documents/91f6c6b0-f1e4-41b1-8273-3fc90b39014a"
        }
    ],
    "ClaimHistory": [
        {
            "Status": "Filed",
            "Date": "2025-03-11T14:40:18Z",
            "Notes": "Initial claim filed"
        },
        {
            "Status": "In Review",
            "Date": "2025-03-16T14:40:18Z",
            "Notes": "Claim is being reviewed"
        },
        {
            "Status": "Approved",
            "Date": "2025-03-21T14:40:18Z",
            "Notes": "Claim approved"
        }
    ],
    "FraudLikelihood": "low"
}