{
    "ClaimID": "bc7c1ef1-315f-41e2-8365-e518f835b66d",
    "PolicyID": "9d5056bb-035b-4a6d-a71b-4fe825194c14",
    "EffectiveDates": {
        "StartDate": "2024-01-04",
        "EndDate": "2025-01-03"
    },
    "PolicyHolder": {
        "PolicyHolderID": "f61e09f1-2d61-4b05-b10e-5f7b4ef6c799",
        "Name": "Ashley Evans",
        "PolicyNumber": "9d5056bb-035b-4a6d-a71b-4fe825194c14",
        "ContactInformation": {
            "Phone": "001-363-788-9689",
            "Email": "nwaters@example.net",
            "Address": "733 Jeffrey Parks\nEast Brian, MP 16771"
        }
    },
    "AccidentDetails": {
        "Date": "2024-12-29",
        "Location": "0945 Flynn Gardens Suite 450\nSouth Sandramouth, NH 63997",
        "Description": "Explain you father wide term point. Recognize bag admit something back day. On gun difference country believe source."
    },
    "Coverage": {
        "BIL": {
            "CoverageLimit": 50000,
            "ClaimedAmount": 56747
        },
        "PDL": {
            "CoverageLimit": 100000,
            "ClaimedAmount": 3050
        },
        "PIP": {
            "CoverageLimit": 50000,
            "ClaimedAmount": 26832
        },
        "CollisionCoverage": {
            "CoverageLimit": 200000,
            "ClaimedAmount": 4151
        },
        "ComprehensiveCoverage": {
            "CoverageLimit": 200000,
            "ClaimedAmount": 5376
        }
    },
    "ClaimStatus": "Approved",
    "ClaimAmounts": {
        "TotalClaimed": 21658,
        "TotalApproved": 19979
    },
    "AdjusterDetails": {
        "Name": "Andrea Dominguez",
        "ContactInformation": {
            "Phone": "+1-846-971-2477x408",
            "Email": "brittany43@example.org"
        }
    },
    "SupportingDocuments": [
        {
            "DocumentType": "Repair Estimate",
            "DocumentURL": "http://example.com/documents/a29dbf72-4ade-4d48-ad70-70e021019bca"
        }
    ],
    "ClaimHistory": [
        {
            "Status": "Filed",
            "Date": "2024-12-29T14:40:19Z",
            "Notes": "Initial claim filed"
        },
        {
            "Status": "In Review",
            "Date": "2025-01-03T14:40:19Z",
            "Notes": "Claim is being reviewed"
        },
        {
            "Status": "Approved",
            "Date": "2025-01-08T14:40:19Z",
            "Notes": "Claim approved"
        }
    ],
    "FraudLikelihood": "low"
}