{
    "ClaimID": "be4c22a1-3ba2-4934-bd61-b2faa24f6068",
    "PolicyID": "7414f48a-acef-4037-896e-d66ef15c19d3",
    "EffectiveDates": {
        "StartDate": "2023-11-18",
        "EndDate": "2024-11-17"
    },
    "PolicyHolder": {
        "PolicyHolderID": "e84f6c22-24b3-4034-bc7a-572ae1407391",
        "Name": "Sonya Jackson",
        "PolicyNumber": "7414f48a-acef-4037-896e-d66ef15c19d3",
        "ContactInformation": {
            "Phone": "(442)321-3282x2644",
            "Email": "danieltodd@example.net",
            "Address": "63661 Jones Manor\nLeslieville, TX 12720"
        }
    },
    "AccidentDetails": {
        "Date": "2024-09-21",
        "Location": "6389 Armstrong Corner\nEast Brandystad, SD 27246",
        "Description": "Window him physical hot cold call those message.\nWhich quickly never yard form house good. Impact cause identify style analysis."
    },
    "Coverage": {
        "BIL": {
            "CoverageLimit": 20000,
            "ClaimedAmount": 16910
        },
        "PDL": {
            "CoverageLimit": 100000,
            "ClaimedAmount": 5654
        },
        "PIP": {
            "CoverageLimit": 50000,
            "ClaimedAmount": 2502
        },
        "CollisionCoverage": {
            "CoverageLimit": 50000,
            "ClaimedAmount": 13649
        },
        "ComprehensiveCoverage": {
            "CoverageLimit": 50000,
            "ClaimedAmount": 6599
        }
    },
    "ClaimStatus": "Approved",
    "ClaimAmounts": {
        "TotalClaimed": 63769,
        "TotalApproved": 15283
    },
    "AdjusterDetails": {
        "Name": "Heather Calderon",
        "ContactInformation": {
            "Phone": "771-959-5830",
            "Email": "john35@example.com"
        }
    },
    "SupportingDocuments": [
        {
            "DocumentType": "Police Report",
            "DocumentURL": "http://example.com/documents/c8bc3672-162e-4ecd-853c-a7a69aac1417"
        }
    ],
    "ClaimHistory": [
        {
            "Status": "Filed",
            "Date": "2024-09-21T14:40:18Z",
            "Notes": "Initial claim filed"
        },
        {
            "Status": "In Review",
            "Date": "2024-09-26T14:40:18Z",
            "Notes": "Claim is being reviewed"
        },
        {
            "Status": "Approved",
            "Date": "2024-10-01T14:40:18Z",
            "Notes": "Claim approved"
        }
    ],
    "FraudLikelihood": "low"
}