{
    "ClaimID": "cefcd770-2537-4fab-9241-cb85cf0ceda4",
    "PolicyID": "90356d98-4a9f-4775-9a86-c5ca182c93f1",
    "EffectiveDates": {
        "StartDate": "2024-07-17",
        "EndDate": "2025-07-17"
    },
    "PolicyHolder": {
        "PolicyHolderID": "0b22081f-a941-455b-9e91-d078ff0b0d74",
        "Name": "Nicholas Mitchell",
        "PolicyNumber": "90356d98-4a9f-4775-9a86-c5ca182c93f1",
        "ContactInformation": {
            "Phone": "(296)578-1714x28056",
            "Email": "gregorygonzales@example.com",
            "Address": "3066 Judy Alley Suite 553\nJacksonton, MN 18066"
        }
    },
    "AccidentDetails": {
        "Date": "2025-05-24",
        "Location": "35307 Morgan Forest\nHessmouth, TN 06796",
        "Description": "Main possible represent. Design then meet really among.\nBlood tree whom determine learn. Research effect glass great forget. Although different where might wrong difference while."
    },
    "Coverage": {
        "BIL": {
            "CoverageLimit": 20000,
            "ClaimedAmount": 17127
        },
        "PDL": {
            "CoverageLimit": 100000,
            "ClaimedAmount": 3090
        },
        "PIP": {
            "CoverageLimit": 100000,
            "ClaimedAmount": 41889
        },
        "CollisionCoverage": {
            "CoverageLimit": 200000,
            "ClaimedAmount": 7189
        },
        "ComprehensiveCoverage": {
            "CoverageLimit": 20000,
            "ClaimedAmount": 168820
        }
    },
    "ClaimStatus": "In Review",
    "ClaimAmounts": {
        "TotalClaimed": 160916,
        "TotalApproved": 5984
    },
    "AdjusterDetails": {
        "Name": "Danielle Juarez",
        "ContactInformation": {
            "Phone": "(725)451-1769x09434",
            "Email": "mtorres@example.org"
        }
    },
    "SupportingDocuments": [
        {
            "DocumentType": "Repair Estimate",
            "DocumentURL": "http://example.com/documents/8806dcac-eaa1-46ce-b13b-953c1363565e"
        }
    ],
    "ClaimHistory": [
        {
            "Status": "Filed",
            "Date": "2025-05-24T14:40:19Z",
            "Notes": "Initial claim filed"
        },
        {
            "Status": "In Review",
            "Date": "2025-05-29T14:40:19Z",
            "Notes": "Claim is being reviewed"
        },
        {
            "Status": "Approved",
            "Date": "2025-06-03T14:40:19Z",
            "Notes": "Claim approved"
        }
    ],
    "FraudLikelihood": "low"
}