{
    "ClaimID": "db73ae54-863f-42d7-868f-875e1f50cda8",
    "PolicyID": "446942ad-2327-410c-b66c-4a134c04e59e",
    "EffectiveDates": {
        "StartDate": "2024-05-23",
        "EndDate": "2025-05-23"
    },
    "PolicyHolder": {
        "PolicyHolderID": "8d51ac88-8d3a-4d73-9192-48892933f063",
        "Name": "Lee Barnett",
        "PolicyNumber": "446942ad-2327-410c-b66c-4a134c04e59e",
        "ContactInformation": {
            "Phone": "593.419.0568x7571",
            "Email": "lcarter@example.net",
            "Address": "558 Tara Knoll\nNew Barbaraville, FM 19814"
        }
    },
    "AccidentDetails": {
        "Date": "2025-03-22",
        "Location": "9546 Stephanie Dam\nJoshuaport, MT 29739",
        "Description": "Receive court skill simply resource miss expect. Environment anyone west call. Happen stuff sense choose training. Health necessary analysis public voice."
    },
    "Coverage": {
        "BIL": {
            "CoverageLimit": 10000,
            "ClaimedAmount": 6102
        },
        "PDL": {
            "CoverageLimit": 200000,
            "ClaimedAmount": 18859
        },
        "PIP": {
            "CoverageLimit": 200000,
            "ClaimedAmount": 9612
        },
        "CollisionCoverage": {
            "CoverageLimit": 20000,
            "ClaimedAmount": 2661
        },
        "ComprehensiveCoverage": {
            "CoverageLimit": 200000,
            "ClaimedAmount": 173086
        }
    },
    "ClaimStatus": "Approved",
    "ClaimAmounts": {
        "TotalClaimed": 63805,
        "TotalApproved": 36373
    },
    "AdjusterDetails": {
        "Name": "Lisa Cole",
        "ContactInformation": {
            "Phone": "(899)960-2319",
            "Email": "zhudson@example.org"
        }
    },
    "SupportingDocuments": [
        {
            "DocumentType": "Repair Estimate",
            "DocumentURL": "http://example.com/documents/d7fdd89b-008b-4e4f-83c0-5cbdea447b36"
        }
    ],
    "ClaimHistory": [
        {
            "Status": "Filed",
            "Date": "2025-03-22T14:39:15Z",
            "Notes": "Initial claim filed"
        },
        {
            "Status": "In Review",
            "Date": "2025-03-27T14:39:15Z",
            "Notes": "Claim is being reviewed"
        },
        {
            "Status": "Approved",
            "Date": "2025-04-01T14:39:15Z",
            "Notes": "Claim approved"
        }
    ],
    "FraudLikelihood": "low"
}