{
    "ClaimID": "f1bf13f7-d32d-44ff-bcbf-05e541d1a8f3",
    "PolicyID": "589364c0-ed81-4b91-ba1d-736aff68c0ed",
    "EffectiveDates": {
        "StartDate": "2023-11-10",
        "EndDate": "2024-11-09"
    },
    "PolicyHolder": {
        "PolicyHolderID": "21068843-1d1e-4045-afea-674e862587e7",
        "Name": "David Hall",
        "PolicyNumber": "589364c0-ed81-4b91-ba1d-736aff68c0ed",
        "ContactInformation": {
            "Phone": "635-614-8182",
            "Email": "alexander77@example.org",
            "Address": "561 Barrett Coves Suite 470\nLake Robert, NV 30472"
        }
    },
    "AccidentDetails": {
        "Date": "2024-01-27",
        "Location": "715 Gaines Way Apt. 004\nLake Michael, LA 71405",
        "Description": "Degree raise can local threat drive issue inside. Team second technology next product decide.\nDifficult attack including happy far them community.\nPiece person without theory learn."
    },
    "Coverage": {
        "BIL": {
            "CoverageLimit": 20000,
            "ClaimedAmount": 17180
        },
        "PDL": {
            "CoverageLimit": 20000,
            "ClaimedAmount": 44233
        },
        "PIP": {
            "CoverageLimit": 10000,
            "ClaimedAmount": 65253
        },
        "CollisionCoverage": {
            "CoverageLimit": 200000,
            "ClaimedAmount": 1088
        },
        "ComprehensiveCoverage": {
            "CoverageLimit": 10000,
            "ClaimedAmount": 27218
        }
    },
    "ClaimStatus": "Approved",
    "ClaimAmounts": {
        "TotalClaimed": 21678,
        "TotalApproved": 9602
    },
    "AdjusterDetails": {
        "Name": "Deborah Mullen",
        "ContactInformation": {
            "Phone": "(895)769-5810x6362",
            "Email": "dsmith@example.org"
        }
    },
    "SupportingDocuments": [
        {
            "DocumentType": "Police Report",
            "DocumentURL": "http://example.com/documents/efb57b2c-f79b-4f25-8222-c82937c7d458"
        }
    ],
    "ClaimHistory": [
        {
            "Status": "Filed",
            "Date": "2024-01-27T14:40:19Z",
            "Notes": "Initial claim filed"
        },
        {
            "Status": "In Review",
            "Date": "2024-02-01T14:40:19Z",
            "Notes": "Claim is being reviewed"
        },
        {
            "Status": "Approved",
            "Date": "2024-02-06T14:40:19Z",
            "Notes": "Claim approved"
        }
    ],
    "FraudLikelihood": "low"
}